phaseportrait/Cobweb.py
phaseportrait/Map1D.py
phaseportrait/PhasePortrait2D.py
phaseportrait/PhasePortrait3D.py
phaseportrait/PhasePortraitManager.py
phaseportrait/Trajectories2D.py
phaseportrait/Trajectories3D.py
phaseportrait/__init__.py
phaseportrait/exceptions/__init__.py
phaseportrait/exceptions/exceptions.py
phaseportrait/generators_base/__init__.py
phaseportrait/generators_base/generator_base.py
phaseportrait/maps/__init__.py
phaseportrait/maps/map.py
phaseportrait/nullclines/__init__.py
phaseportrait/nullclines/nullclines.py
phaseportrait/sliders/__init__.py
phaseportrait/sliders/sliders.py
phaseportrait/streamlines/__init__.py
phaseportrait/streamlines/size_gradient.py
phaseportrait/streamlines/streamlines_base.py
phaseportrait/streamlines/velocity_color_gradient.py
phaseportrait/trajectories/__init__.py
phaseportrait/trajectories/rungekutta.py
phaseportrait/trajectories/trajectory.py
phaseportrait/utils/__init__.py
phaseportrait/utils/manager.py
phaseportrait/utils/utils.py
phaseportrait-1.3.1.dist-info/licenses/LICENSE
phaseportrait-1.3.1.dist-info/METADATA
phaseportrait-1.3.1.dist-info/WHEEL
phaseportrait-1.3.1.dist-info/top_level.txt
phaseportrait-1.3.1.dist-info/RECORD
