Metadata-Version: 2.4
Name: phaseportrait
Version: 1.3.1
Summary: A python package for visualizing non-linear dynamics and chaos. (2D phase portraits, 3D chaotic trajectories, Maps, Cobweb plots...)
Author-email: Víctor Loras <vhloras@gmail.com>, Unai Lería <unaileria@gmail.com>
Maintainer-email: Víctor Loras <vhloras@gmail.com>, Unai Lería <unaileria@gmail.com>
License: MIT license
Project-URL: Documentation, https://phaseportrait.github.io/
Project-URL: GitHub, https://github.com/phaseportrait/phaseportrait
Project-URL: GUI, https://github.com/phaseportrait/phaseportrait-gui
Classifier: Intended Audience :: Education
Classifier: Intended Audience :: Science/Research
Classifier: Programming Language :: Python :: 3.8
Classifier: Programming Language :: Python :: 3.9
Classifier: Programming Language :: Python :: 3.10
Classifier: Programming Language :: Python :: 3.11
Classifier: Programming Language :: Python :: 3.12
Classifier: License :: OSI Approved :: MIT License
Classifier: Operating System :: OS Independent
Classifier: Topic :: Education
Classifier: Topic :: Scientific/Engineering
Classifier: Topic :: Scientific/Engineering :: Physics
Classifier: Topic :: Scientific/Engineering :: Visualization
Requires-Python: >=3.8
License-File: LICENSE
Requires-Dist: numpy
Requires-Dist: matplotlib
Requires-Dist: scipy
Dynamic: license-file
